kernel_sidecar/__init__.py
kernel_sidecar/actions.py
kernel_sidecar/cli.py
kernel_sidecar/client.py
kernel_sidecar/comms.py
kernel_sidecar/handlers/__init__.py
kernel_sidecar/handlers/base.py
kernel_sidecar/handlers/debug.py
kernel_sidecar/handlers/output.py
kernel_sidecar/log_utils.py
kernel_sidecar/models/__init__.py
kernel_sidecar/models/messages.py
kernel_sidecar/models/notebook.py
kernel_sidecar/models/requests.py
kernel_sidecar/nb_builder.py
kernel_sidecar/settings.py
kernel_sidecar-1.0.0.dist-info/LICENSE
kernel_sidecar-1.0.0.dist-info/METADATA
kernel_sidecar-1.0.0.dist-info/WHEEL
kernel_sidecar-1.0.0.dist-info/entry_points.txt
kernel_sidecar-1.0.0.dist-info/RECORD
