Metadata-Version: 2.1
Name: kernel-sidecar
Version: 1.0.0
Summary: A sidecar 
Home-page: https://github.com/kafonek/kernel-sidecar
License: MIT
Author: Matt Kafonek
Author-email: matt.kafonek@noteable.io
Requires-Python: >=3.9,<4.0
Classifier: License :: OSI Approved :: MIT License
Classifier: Programming Language :: Python :: 3
Classifier: Programming Language :: Python :: 3.9
Classifier: Programming Language :: Python :: 3.10
Classifier: Programming Language :: Python :: 3.11
Provides-Extra: cli
Requires-Dist: jupyter-client (>=7.3.4)
Requires-Dist: pydantic (>2)
Requires-Dist: pydantic-settings (>2)
Requires-Dist: structlog ; extra == "cli"
Requires-Dist: typer ; extra == "cli"
Project-URL: Repository, https://github.com/kafonek/kernel-sidecar
